.gitignore
.travis.yml
LICENSE
README.md
requirements.txt
setup.py
braviaproapi/__init__.py
braviaproapi/braviaclient.py
braviaproapi.egg-info/PKG-INFO
braviaproapi.egg-info/SOURCES.txt
braviaproapi.egg-info/dependency_links.txt
braviaproapi.egg-info/requires.txt
braviaproapi.egg-info/top_level.txt
braviaproapi/bravia/__init__.py
braviaproapi/bravia/appcontrol.py
braviaproapi/bravia/audio.py
braviaproapi/bravia/avcontent.py
braviaproapi/bravia/encryption.py
braviaproapi/bravia/http.py
braviaproapi/bravia/remote.py
braviaproapi/bravia/system.py
braviaproapi/bravia/util.py
braviaproapi/bravia/videoscreen.py
braviaproapi/bravia/errors/__init__.py
braviaproapi/bravia/errors/apierror.py
braviaproapi/bravia/errors/errorhandling.py
braviaproapi/bravia/errors/httperror.py
braviaproapi/bravia/errors/internalerror.py
docs/Makefile
docs/make.bat
docs/source/braviaproapi.bravia.appcontrol.rst
docs/source/braviaproapi.bravia.audio.rst
docs/source/braviaproapi.bravia.avcontent.rst
docs/source/braviaproapi.bravia.encryption.rst
docs/source/braviaproapi.bravia.errors.apierror.rst
docs/source/braviaproapi.bravia.errors.applauncherror.rst
docs/source/braviaproapi.bravia.errors.encryptionerror.rst
docs/source/braviaproapi.bravia.errors.httperror.rst
docs/source/braviaproapi.bravia.errors.internalerror.rst
docs/source/braviaproapi.bravia.errors.invalidstateerror.rst
docs/source/braviaproapi.bravia.errors.languagenotsupportederror.rst
docs/source/braviaproapi.bravia.errors.nofocusedtextfielderror.rst
docs/source/braviaproapi.bravia.errors.rst
docs/source/braviaproapi.bravia.errors.targetnotsupportederror.rst
docs/source/braviaproapi.bravia.errors.volumeoutofrangeerror.rst
docs/source/braviaproapi.bravia.http.rst
docs/source/braviaproapi.bravia.remote.rst
docs/source/braviaproapi.bravia.rst
docs/source/braviaproapi.bravia.system.rst
docs/source/braviaproapi.bravia.videoscreen.rst
docs/source/braviaproapi.braviaclient.rst
docs/source/braviaproapi.rst
docs/source/conf.py
docs/source/gettingstarted.rst
docs/source/index.rst