Metadata-Version: 2.1
Name: braviaproapi
Version: 0.1.3
Summary: Library for controlling Sony Bravia TVs utilizing their Bravia Professional API.
Home-page: https://github.com/BrandonDusseau/py-bravia-pro-api
Author: Brandon Dusseau
Author-email: brandon.dusseau+pypi@gmail.com
License: UNKNOWN
Keywords: sony bravia television remote control library
Platform: UNKNOWN
Classifier: Programming Language :: Python :: 3.7
Classifier: License :: OSI Approved :: MIT License
Classifier: Operating System :: OS Independent 
Classifier: Development Status :: 4 - Beta
Classifier: Intended Audience :: Developers
Classifier: Topic :: Software Development :: Libraries :: Python Modules
